fastinit/__init__.py
fastinit/cli.py
fastinit/utils.py
fastinit/commands/__init__.py
fastinit/commands/init.py
fastinit/commands/new.py
fastinit/generators/__init__.py
fastinit/generators/component.py
fastinit/generators/project.py
fastinit/models/__init__.py
fastinit/models/config.py
fastinit/templates/Dockerfile.jinja
fastinit/templates/README.md.jinja
fastinit/templates/__init__.py
fastinit/templates/alembic.ini.jinja
fastinit/templates/docker-compose.yml.jinja
fastinit/templates/dockerignore.jinja
fastinit/templates/env.example.jinja
fastinit/templates/gitignore.jinja
fastinit/templates/main.py.jinja
fastinit/templates/pyproject.toml.jinja
fastinit/templates/requirements.txt.jinja
fastinit/templates/alembic/README.jinja
fastinit/templates/alembic/env.py.jinja
fastinit/templates/alembic/script.py.mako.jinja
fastinit/templates/api/deps.py.jinja
fastinit/templates/api/routes/health.py.jinja
fastinit/templates/components/model.py.jinja
fastinit/templates/components/route.py.jinja
fastinit/templates/components/schema.py.jinja
fastinit/templates/components/service.py.jinja
fastinit/templates/core/__init__.py.jinja
fastinit/templates/core/config.py.jinja
fastinit/templates/core/security.py.jinja
fastinit/templates/db/base.py.jinja
fastinit/templates/db/session.py.jinja
fastinit/templates/models/__init__.py.jinja
fastinit-0.2.0.dist-info/licenses/LICENSE
fastinit-0.2.0.dist-info/METADATA
fastinit-0.2.0.dist-info/WHEEL
fastinit-0.2.0.dist-info/entry_points.txt
fastinit-0.2.0.dist-info/top_level.txt
fastinit-0.2.0.dist-info/RECORD
