Metadata-Version: 2.4
Name: fastinit
Version: 0.2.0
Summary: A CLI tool to bootstrap FastAPI applications with best practices
Author-email: Claes Nymand Nilsson <your.email@example.com>
License-Expression: MIT
Project-URL: Homepage, https://github.com/claesnn/fastinit
Project-URL: Documentation, https://github.com/claesnn/fastinit#readme
Project-URL: Repository, https://github.com/claesnn/fastinit
Keywords: fastapi,cli,bootstrap,starter,typer
Classifier: Development Status :: 4 - Beta
Classifier: Intended Audience :: Developers
Classifier: Programming Language :: Python :: 3
Classifier: Programming Language :: Python :: 3.8
Classifier: Programming Language :: Python :: 3.9
Classifier: Programming Language :: Python :: 3.10
Classifier: Programming Language :: Python :: 3.11
Classifier: Programming Language :: Python :: 3.12
Requires-Python: >=3.8
License-File: LICENSE
Requires-Dist: typer[all]>=0.9.0
Requires-Dist: rich>=13.0.0
Requires-Dist: jinja2>=3.1.0
Provides-Extra: dev
Requires-Dist: pytest>=7.0.0; extra == "dev"
Requires-Dist: black>=23.0.0; extra == "dev"
Requires-Dist: flake8>=6.0.0; extra == "dev"
Requires-Dist: mypy>=1.0.0; extra == "dev"
Dynamic: license-file
